lazyOfAPI/__init__.py
lazyOfAPI/OpenFrpAPI.py
lazyofapi-0.1.5.dist-info/LICENSE
lazyofapi-0.1.5.dist-info/METADATA
lazyofapi-0.1.5.dist-info/WHEEL
lazyofapi-0.1.5.dist-info/RECORD
